OutText_preprocessing/__init__.py
OutText_preprocessing/outlier_removal.py
OutText_preprocessing/text_preprocessing.py
tests/__init__.py
tests/test_outlier_removal.py
tests/test_text_prepeocessing.py
OutText_preprocessing-1.0.5.dist-info/LICENSE
OutText_preprocessing-1.0.5.dist-info/METADATA
OutText_preprocessing-1.0.5.dist-info/WHEEL
OutText_preprocessing-1.0.5.dist-info/top_level.txt
OutText_preprocessing-1.0.5.dist-info/RECORD
