Metadata-Version: 2.1
Name: OutText-preprocessing
Version: 1.0.5
Summary: ✨ A powerful Python package for outlier removal and text preprocessing
Home-page: https://github.com/Anurag-raj03/OutText_preprocessing_library
Author: Anurag Raj
Author-email: anuragraj4483@gmail.com
License: MIT
Platform: UNKNOWN
Classifier: Development Status :: 4 - Beta
Classifier: Intended Audience :: Developers
Classifier: Topic :: Scientific/Engineering :: Information Analysis
Classifier: Programming Language :: Python :: 3
Classifier: License :: OSI Approved :: MIT License
Classifier: Operating System :: OS Independent
Requires-Python: >=3.6
License-File: LICENSE
Requires-Dist: pandas
Requires-Dist: numpy
Requires-Dist: scipy
Requires-Dist: scikit-learn
Requires-Dist: nltk
Requires-Dist: emoji
Requires-Dist: autocorrect
Requires-Dist: pytest
